AesCrypt/__init__.py
AesCrypt/__version__.py
AesCrypt/aesDemo.py
AesCrypt-0.1.0.dist-info/METADATA
AesCrypt-0.1.0.dist-info/RECORD
AesCrypt-0.1.0.dist-info/WHEEL
AesCrypt-0.1.0.dist-info/top_level.txt
